Workbook

Sheet ANALISA
C1: GRAMEDIA
C2: REKONSILIASI OMSET BULAN :
C3: NOMOR REKENING : | AF3: CARD GROUPING | AP3: E-WALLET GROUPING
C4: versi 1.1 (final) | E4: 1 | F4: 1 | G4: 10 | H4: 12 | I4: 13 | J4: 14 | K4: 15 | N4: 42 | O4: 44 | P4: 9 | Q4: 99 | AF4: 16 | AG4: 20 | AH4: 21 | AI4: 22 | AJ4: 23 | AK4: 24 | AL4: 26 | AM4: 28 | AN4: 30 | AO4: 31 | AP4: 34 | AQ4: 35 | AR4: 36 | AS4: 37 | AT4: 38 | AU4: 39 | AV4: 40 | AW4: 41 | AX4: 98
A5: DATE COPY | B5: DATE CONVERT SSRS | C5: DATE | D5: TRANSACTION | E5: CASH | F5: SAFE | G5: INT | H5: EXT | I5: CUSTOMER | J5: LOYALTY | K5: MOBILE | L5: CARD | M5: E-WALLET | N5: HCI | O5: SODEXO | P5: BT SLIP | Q5: TENDER REMOVE | R5: DIFFERENCE | S5: DEPOSIT | T5: FIRST | U5: DATE | V5: SECOND | W5: DATE | X5: SELISIH | Y5: DEPOSITED | Z5: BALANCE | AA5: TGL | AB5: STATEMENT | AC5: BANK | AD5: DESCRIPTION | AE5: CHECK | AF5: Debit | AG5: BCA | AH5: Mandiri | AI5: CIMB | AJ5: BNI | AK5: BRI | AL5: Citibank | AM5: BTN | AN5: DKI | AO5: BSI | AP5: OVO | AQ5: GOPAY | AR5: SHOPEE PAY | AS5: LINK AJA | AT5: INDODANA | AU5: KREDIVO | AV5: ATOME | AW5: DANA | AX5: OTHER
C6: OMSET | D6: AMOUNT D365 | E6: AMOUNT | F6: AMOUNT | G6: AMOUNT | H6: AMOUNT | I6: ACCOUNT IDR | J6: IDR | K6: POS | L6: AMOUNT | M6: AMOUNT | N6: AMOUNT | O6: PLUXIE | P6: AMOUNT | Q6: AMOUNT | R6: AMOUNT | S6: IN TRANSIT | T6: DEPOSIT | V6: DEPOSIT | Z6: SETTLE | AB6: NUMBER | AC6: DEPOSIT | AF6: Card | AG6: Debit | AH6: Debit | AI6: Debit | AJ6: Debit | AK6: Debit | AM6: Debit | AN6: Debit
A8: =C8 -> 46266 | B8: =TEXT(A8,"DD-MMM-YYYY DDDD") -> 01-Sep-2026 Tuesday | C8: 46266 | D8: =SUMIF(statement!$K:$K,ANALISA!AA8,statement!$F:$F) -> 0 | E8: =SUMIFS(statement!$I:$I,statement!$K:$K,ANALISA!$AA8, statement!$B:$B,ANALISA!E$4) -> 0 | F8: =SUMIFS(statement!$H:$H,statement!$K:$K,ANALISA!$AA8, statement!$B:$B,ANALISA!F$4) -> 0 | G8: =SUMIFS(statement!$I:$I,statement!$K:$K,ANALISA!$AA8, statement!$B:$B,ANALISA!G$4) -> 0 | H8: =SUMIFS(statement!$I:$I,statement!$K:$K,ANALISA!$AA8, statement!$B:$B,ANALISA!H$4) -> 0 | I8: =SUMIFS(statement!$I:$I,statement!$K:$K,ANALISA!$AA8, statement!$B:$B,ANALISA!I$4) -> 0 | J8: =SUMIFS(statement!$I:$I,statement!$K:$K,ANALISA!$AA8, statement!$B:$B,ANALISA!J$4) -> 0 | K8: =SUMIFS(statement!$I:$I,statement!$K:$K,ANALISA!$AA8, statement!$B:$B,ANALISA!K$4) -> 0 | L8: =AF8+AG8+AH8+AI8+AJ8+AK8+AM8+AN8+AO8+AL8 -> 0 | M8: =SUMIFS(statement!$I:$I,statement!$K:$K,ANALISA!$AA8, statement!$B:$B,ANALISA!M$4) -> 0 | N8: =SUMIFS(statement!$I:$I,statement!$K:$K,ANALISA!$AA8, statement!$B:$B,ANALISA!N$4) -> 0 | O8: =SUMIFS(statement!$I:$I,statement!$K:$K,ANALISA!$AA8, statement!$B:$B,ANALISA!O$4) -> 0 | P8: =SUMIFS(statement!$I:$I,statement!$K:$K,ANALISA!$AA8, statement!$B:$B,ANALISA!P$4) -> 0 | Q8: =SUMIFS(statement!$I:$I,statement!$K:$K,ANALISA!$AA8, statement!$B:$B,ANALISA!Q$4) -> 0 | R8: =SUMIF(statement!$K:$K,ANALISA!AA8,statement!$J:$J) -> 0 | S8: =D8-G8-H8-I8-J8-N8-P8+R8-K8-L8-M8-O8 -> 0 | T8: =IFERROR(VLOOKUP(S8,RK!$D$1:$E$65536,1,FALSE),0) -> 0 | U8: =VLOOKUP(T8,RK!$D$1:$E$65536,2,FALSE) -> #N/A | W8: =VLOOKUP(V8,RK!$D$1:$E$65536,2,FALSE) -> #N/A | X8: =P8-S8+T8-V8 -> 0 | Y8: 0 | AA8: 1 | AC8: =S8 -> 0 | AD8: =IFERROR(VLOOKUP(AB8,BDEPO!$A:$K,11,FALSE),"-") -> - | AE8: =IF(T8=AC8,"DEPOSITED","BELUM SETOR") -> DEPOSITED | AF8: =SUMIFS(statement!$I:$I,statement!$K:$K,ANALISA!$AA8, statement!$B:$B,ANALISA!AF$4) -> 0 | AG8: =SUMIFS(statement!$I:$I,statement!$K:$K,ANALISA!$AA8, statement!$B:$B,ANALISA!AG$4) -> 0 | AH8: =SUMIFS(statement!$I:$I,statement!$K:$K,ANALISA!$AA8, statement!$B:$B,ANALISA!AH$4) -> 0 | AI8: =SUMIFS(statement!$I:$I,statement!$K:$K,ANALISA!$AA8, statement!$B:$B,ANALISA!AI$4) -> 0 | AJ8: =SUMIFS(statement!$I:$I,statement!$K:$K,ANALISA!$AA8, statement!$B:$B,ANALISA!AJ$4) -> 0 | AK8: =SUMIFS(statement!$I:$I,statement!$K:$K,ANALISA!$AA8, statement!$B:$B,ANALISA!AK$4) -> 0 | AL8: =SUMIFS(statement!$I:$I,statement!$K:$K,ANALISA!$AA8, statement!$B:$B,ANALISA!AL$4) -> 0 | AM8: =SUMIFS(statement!$I:$I,statement!$K:$K,ANALISA!$AA8, statement!$B:$B,ANALISA!AM$4) -> 0 | ... AX8: =SUMIFS(statement!$I:$I,statement!$K:$K,ANALISA!$AA8, statement!$B:$B,ANALISA!AX$4) -> 0
A9: =C9 -> 46267 | B9: =TEXT(A9,"DD-MMM-YYYY DDDD") -> 02-Sep-2026 Wednesday | C9: 46267 | D9: =SUMIF(statement!$K:$K,ANALISA!AA9,statement!$F:$F) -> 0 | E9: =SUMIFS(statement!$I:$I,statement!$K:$K,ANALISA!$AA9, statement!$B:$B,ANALISA!E$4) -> 0 | F9: =SUMIFS(statement!$H:$H,statement!$K:$K,ANALISA!$AA9, statement!$B:$B,ANALISA!F$4) -> 0 | G9: =SUMIFS(statement!$I:$I,statement!$K:$K,ANALISA!$AA9, statement!$B:$B,ANALISA!G$4) -> 0 | H9: =SUMIFS(statement!$I:$I,statement!$K:$K,ANALISA!$AA9, statement!$B:$B,ANALISA!H$4) -> 0 | I9: =SUMIFS(statement!$I:$I,statement!$K:$K,ANALISA!$AA9, statement!$B:$B,ANALISA!I$4) -> 0 | J9: =SUMIFS(statement!$I:$I,statement!$K:$K,ANALISA!$AA9, statement!$B:$B,ANALISA!J$4) -> 0 | K9: =SUMIFS(statement!$I:$I,statement!$K:$K,ANALISA!$AA9, statement!$B:$B,ANALISA!K$4) -> 0 | L9: =AF9+AG9+AH9+AI9+AJ9+AK9+AM9+AN9+AO9+AL9 -> 0 | M9: =SUMIFS(statement!$I:$I,statement!$K:$K,ANALISA!$AA9, statement!$B:$B,ANALISA!M$4) -> 0 | N9: =SUMIFS(statement!$I:$I,statement!$K:$K,ANALISA!$AA9, statement!$B:$B,ANALISA!N$4) -> 0 | O9: =SUMIFS(statement!$I:$I,statement!$K:$K,ANALISA!$AA9, statement!$B:$B,ANALISA!O$4) -> 0 | P9: =SUMIFS(statement!$I:$I,statement!$K:$K,ANALISA!$AA9, statement!$B:$B,ANALISA!P$4) -> 0 | Q9: =SUMIFS(statement!$I:$I,statement!$K:$K,ANALISA!$AA9, statement!$B:$B,ANALISA!Q$4) -> 0 | R9: =SUMIF(statement!$K:$K,ANALISA!AA9,statement!$J:$J) -> 0 | S9: =D9-G9-H9-I9-J9-N9-P9+R9-K9-L9-M9-O9 -> 0 | T9: =IFERROR(VLOOKUP(S9,RK!$D$1:$E$65536,1,FALSE),0) -> 0 | U9: =VLOOKUP(T9,RK!$D$1:$E$65536,2,FALSE) -> #N/A | W9: =VLOOKUP(V9,RK!$D$1:$E$65536,2,FALSE) -> #N/A | X9: =P9-S9+T9-V9 -> 0 | Y9: 0 | Z9: =Z8+S8-Y9 -> 0 | AA9: 2 | AC9: =S9 -> 0 | AD9: =IFERROR(VLOOKUP(AB9,BDEPO!$A:$K,11,FALSE),"-") -> - | AE9: =IF(T9=AC9,"DEPOSITED","BELUM SETOR") -> DEPOSITED | AF9: =SUMIFS(statement!$I:$I,statement!$K:$K,ANALISA!$AA9, statement!$B:$B,ANALISA!AF$4) -> 0 | AG9: =SUMIFS(statement!$I:$I,statement!$K:$K,ANALISA!$AA9, statement!$B:$B,ANALISA!AG$4) -> 0 | AH9: =SUMIFS(statement!$I:$I,statement!$K:$K,ANALISA!$AA9, statement!$B:$B,ANALISA!AH$4) -> 0 | AI9: =SUMIFS(statement!$I:$I,statement!$K:$K,ANALISA!$AA9, statement!$B:$B,ANALISA!AI$4) -> 0 | AJ9: =SUMIFS(statement!$I:$I,statement!$K:$K,ANALISA!$AA9, statement!$B:$B,ANALISA!AJ$4) -> 0 | AK9: =SUMIFS(statement!$I:$I,statement!$K:$K,ANALISA!$AA9, statement!$B:$B,ANALISA!AK$4) -> 0 | AL9: =SUMIFS(statement!$I:$I,statement!$K:$K,ANALISA!$AA9, statement!$B:$B,ANALISA!AL$4) -> 0 | AM9: =SUMIFS(statement!$I:$I,statement!$K:$K,ANALISA!$AA9, statement!$B:$B,ANALISA!AM$4) -> 0 | ... AX9: =SUMIFS(statement!$I:$I,statement!$K:$K,ANALISA!$AA9, statement!$B:$B,ANALISA!AX$4) -> 0
A10: =C10 -> 46268 | B10: =TEXT(A10,"DD-MMM-YYYY DDDD") -> 03-Sep-2026 Thursday | C10: 46268 | D10: =SUMIF(statement!$K:$K,ANALISA!AA10,statement!$F:$F) -> 0 | E10: =SUMIFS(statement!$I:$I,statement!$K:$K,ANALISA!$AA10, statement!$B:$B,ANALISA!E$4) -> 0 | F10: =SUMIFS(statement!$H:$H,statement!$K:$K,ANALISA!$AA10, statement!$B:$B,ANALISA!F$4) -> 0 | G10: =SUMIFS(statement!$I:$I,statement!$K:$K,ANALISA!$AA10, statement!$B:$B,ANALISA!G$4) -> 0 | H10: =SUMIFS(statement!$I:$I,statement!$K:$K,ANALISA!$AA10, statement!$B:$B,ANALISA!H$4) -> 0 | I10: =SUMIFS(statement!$I:$I,statement!$K:$K,ANALISA!$AA10, statement!$B:$B,ANALISA!I$4) -> 0 | J10: =SUMIFS(statement!$I:$I,statement!$K:$K,ANALISA!$AA10, statement!$B:$B,ANALISA!J$4) -> 0 | K10: =SUMIFS(statement!$I:$I,statement!$K:$K,ANALISA!$AA10, statement!$B:$B,ANALISA!K$4) -> 0 | L10: =AF10+AG10+AH10+AI10+AJ10+AK10+AM10+AN10+AO10+AL10 -> 0 | M10: =SUMIFS(statement!$I:$I,statement!$K:$K,ANALISA!$AA10, statement!$B:$B,ANALISA!M$4) -> 0 | N10: =SUMIFS(statement!$I:$I,statement!$K:$K,ANALISA!$AA10, statement!$B:$B,ANALISA!N$4) -> 0 | O10: =SUMIFS(statement!$I:$I,statement!$K:$K,ANALISA!$AA10, statement!$B:$B,ANALISA!O$4) -> 0 | P10: =SUMIFS(statement!$I:$I,statement!$K:$K,ANALISA!$AA10, statement!$B:$B,ANALISA!P$4) -> 0 | Q10: =SUMIFS(statement!$I:$I,statement!$K:$K,ANALISA!$AA10, statement!$B:$B,ANALISA!Q$4) -> 0 | R10: =SUMIF(statement!$K:$K,ANALISA!AA10,statement!$J:$J) -> 0 | S10: =D10-G10-H10-I10-J10-N10-P10+R10-K10-L10-M10-O10 -> 0 | T10: =IFERROR(VLOOKUP(S10,RK!$D$1:$E$65536,1,FALSE),0) -> 0 | U10: =VLOOKUP(T10,RK!$D$1:$E$65536,2,FALSE) -> #N/A | W10: =VLOOKUP(V10,RK!$D$1:$E$65536,2,FALSE) -> #N/A | X10: =P10-S10+T10-V10 -> 0 | Y10: 0 | Z10: =Z9+S9-Y10 -> 0 | AA10: 3 | AC10: =S10 -> 0 | AD10: =IFERROR(VLOOKUP(AB10,BDEPO!$A:$K,11,FALSE),"-") -> - | AE10: =IF(T10=AC10,"DEPOSITED","BELUM SETOR") -> DEPOSITED | AF10: =SUMIFS(statement!$I:$I,statement!$K:$K,ANALISA!$AA10, statement!$B:$B,ANALISA!AF$4) -> 0 | AG10: =SUMIFS(statement!$I:$I,statement!$K:$K,ANALISA!$AA10, statement!$B:$B,ANALISA!AG$4) -> 0 | AH10: =SUMIFS(statement!$I:$I,statement!$K:$K,ANALISA!$AA10, statement!$B:$B,ANALISA!AH$4) -> 0 | AI10: =SUMIFS(statement!$I:$I,statement!$K:$K,ANALISA!$AA10, statement!$B:$B,ANALISA!AI$4) -> 0 | AJ10: =SUMIFS(statement!$I:$I,statement!$K:$K,ANALISA!$AA10, statement!$B:$B,ANALISA!AJ$4) -> 0 | AK10: =SUMIFS(statement!$I:$I,statement!$K:$K,ANALISA!$AA10, statement!$B:$B,ANALISA!AK$4) -> 0 | AL10: =SUMIFS(statement!$I:$I,statement!$K:$K,ANALISA!$AA10, statement!$B:$B,ANALISA!AL$4) -> 0 | AM10: =SUMIFS(statement!$I:$I,statement!$K:$K,ANALISA!$AA10, statement!$B:$B,ANALISA!AM$4) -> 0 | ... AX10: =SUMIFS(statement!$I:$I,statement!$K:$K,ANALISA!$AA10, statement!$B:$B,ANALISA!AX$4) -> 0
A11: =C11 -> 46269 | B11: =TEXT(A11,"DD-MMM-YYYY DDDD") -> 04-Sep-2026 Friday | C11: 46269 | D11: =SUMIF(statement!$K:$K,ANALISA!AA11,statement!$F:$F) -> 0 | E11: =SUMIFS(statement!$I:$I,statement!$K:$K,ANALISA!$AA11, statement!$B:$B,ANALISA!E$4) -> 0 | F11: =SUMIFS(statement!$H:$H,statement!$K:$K,ANALISA!$AA11, statement!$B:$B,ANALISA!F$4) -> 0 | G11: =SUMIFS(statement!$I:$I,statement!$K:$K,ANALISA!$AA11, statement!$B:$B,ANALISA!G$4) -> 0 | H11: =SUMIFS(statement!$I:$I,statement!$K:$K,ANALISA!$AA11, statement!$B:$B,ANALISA!H$4) -> 0 | I11: =SUMIFS(statement!$I:$I,statement!$K:$K,ANALISA!$AA11, statement!$B:$B,ANALISA!I$4) -> 0 | J11: =SUMIFS(statement!$I:$I,statement!$K:$K,ANALISA!$AA11, statement!$B:$B,ANALISA!J$4) -> 0 | K11: =SUMIFS(statement!$I:$I,statement!$K:$K,ANALISA!$AA11, statement!$B:$B,ANALISA!K$4) -> 0 | L11: =AF11+AG11+AH11+AI11+AJ11+AK11+AM11+AN11+AO11+AL11 -> 0 | M11: =SUMIFS(statement!$I:$I,statement!$K:$K,ANALISA!$AA11, statement!$B:$B,ANALISA!M$4) -> 0 | N11: =SUMIFS(statement!$I:$I,statement!$K:$K,ANALISA!$AA11, statement!$B:$B,ANALISA!N$4) -> 0 | O11: =SUMIFS(statement!$I:$I,statement!$K:$K,ANALISA!$AA11, statement!$B:$B,ANALISA!O$4) -> 0 | P11: =SUMIFS(statement!$I:$I,statement!$K:$K,ANALISA!$AA11, statement!$B:$B,ANALISA!P$4) -> 0 | Q11: =SUMIFS(statement!$I:$I,statement!$K:$K,ANALISA!$AA11, statement!$B:$B,ANALISA!Q$4) -> 0 | R11: =SUMIF(statement!$K:$K,ANALISA!AA11,statement!$J:$J) -> 0 | S11: =D11-G11-H11-I11-J11-N11-P11+R11-K11-L11-M11-O11 -> 0 | T11: =IFERROR(VLOOKUP(S11,RK!$D$1:$E$65536,1,FALSE),0) -> 0 | U11: =VLOOKUP(T11,RK!$D$1:$E$65536,2,FALSE) -> #N/A | W11: =VLOOKUP(V11,RK!$D$1:$E$65536,2,FALSE) -> #N/A | X11: =P11-S11+T11-V11 -> 0 | Y11: 0 | Z11: =Z10+S10-Y11 -> 0 | AA11: 4 | AC11: =S11 -> 0 | AD11: =IFERROR(VLOOKUP(AB11,BDEPO!$A:$K,11,FALSE),"-") -> - | AE11: =IF(T11=AC11,"DEPOSITED","BELUM SETOR") -> DEPOSITED | AF11: =SUMIFS(statement!$I:$I,statement!$K:$K,ANALISA!$AA11, statement!$B:$B,ANALISA!AF$4) -> 0 | AG11: =SUMIFS(statement!$I:$I,statement!$K:$K,ANALISA!$AA11, statement!$B:$B,ANALISA!AG$4) -> 0 | AH11: =SUMIFS(statement!$I:$I,statement!$K:$K,ANALISA!$AA11, statement!$B:$B,ANALISA!AH$4) -> 0 | AI11: =SUMIFS(statement!$I:$I,statement!$K:$K,ANALISA!$AA11, statement!$B:$B,ANALISA!AI$4) -> 0 | AJ11: =SUMIFS(statement!$I:$I,statement!$K:$K,ANALISA!$AA11, statement!$B:$B,ANALISA!AJ$4) -> 0 | AK11: =SUMIFS(statement!$I:$I,statement!$K:$K,ANALISA!$AA11, statement!$B:$B,ANALISA!AK$4) -> 0 | AL11: =SUMIFS(statement!$I:$I,statement!$K:$K,ANALISA!$AA11, statement!$B:$B,ANALISA!AL$4) -> 0 | AM11: =SUMIFS(statement!$I:$I,statement!$K:$K,ANALISA!$AA11, statement!$B:$B,ANALISA!AM$4) -> 0 | ... AX11: =SUMIFS(statement!$I:$I,statement!$K:$K,ANALISA!$AA11, statement!$B:$B,ANALISA!AX$4) -> 0
A12: =C12 -> 46270 | B12: =TEXT(A12,"DD-MMM-YYYY DDDD") -> 05-Sep-2026 Saturday | C12: 46270 | D12: =SUMIF(statement!$K:$K,ANALISA!AA12,statement!$F:$F) -> 0 | E12: =SUMIFS(statement!$I:$I,statement!$K:$K,ANALISA!$AA12, statement!$B:$B,ANALISA!E$4) -> 0 | F12: =SUMIFS(statement!$H:$H,statement!$K:$K,ANALISA!$AA12, statement!$B:$B,ANALISA!F$4) -> 0 | G12: =SUMIFS(statement!$I:$I,statement!$K:$K,ANALISA!$AA12, statement!$B:$B,ANALISA!G$4) -> 0 | H12: =SUMIFS(statement!$I:$I,statement!$K:$K,ANALISA!$AA12, statement!$B:$B,ANALISA!H$4) -> 0 | I12: =SUMIFS(statement!$I:$I,statement!$K:$K,ANALISA!$AA12, statement!$B:$B,ANALISA!I$4) -> 0 | J12: =SUMIFS(statement!$I:$I,statement!$K:$K,ANALISA!$AA12, statement!$B:$B,ANALISA!J$4) -> 0 | K12: =SUMIFS(statement!$I:$I,statement!$K:$K,ANALISA!$AA12, statement!$B:$B,ANALISA!K$4) -> 0 | L12: =AF12+AG12+AH12+AI12+AJ12+AK12+AM12+AN12+AO12+AL12 -> 0 | M12: =SUMIFS(statement!$I:$I,statement!$K:$K,ANALISA!$AA12, statement!$B:$B,ANALISA!M$4) -> 0 | N12: =SUMIFS(statement!$I:$I,statement!$K:$K,ANALISA!$AA12, statement!$B:$B,ANALISA!N$4) -> 0 | O12: =SUMIFS(statement!$I:$I,statement!$K:$K,ANALISA!$AA12, statement!$B:$B,ANALISA!O$4) -> 0 | P12: =SUMIFS(statement!$I:$I,statement!$K:$K,ANALISA!$AA12, statement!$B:$B,ANALISA!P$4) -> 0 | Q12: =SUMIFS(statement!$I:$I,statement!$K:$K,ANALISA!$AA12, statement!$B:$B,ANALISA!Q$4) -> 0 | R12: =SUMIF(statement!$K:$K,ANALISA!AA12,statement!$J:$J) -> 0 | S12: =D12-G12-H12-I12-J12-N12-P12+R12-K12-L12-M12-O12 -> 0 | T12: =IFERROR(VLOOKUP(S12,RK!$D$1:$E$65536,1,FALSE),0) -> 0 | U12: =VLOOKUP(T12,RK!$D$1:$E$65536,2,FALSE) -> #N/A | W12: =VLOOKUP(V12,RK!$D$1:$E$65536,2,FALSE) -> #N/A | X12: =P12-S12+T12-V12 -> 0 | Y12: 0 | Z12: =Z11+S11-Y12 -> 0 | AA12: 5 | AC12: =S12 -> 0 | AD12: =IFERROR(VLOOKUP(AB12,BDEPO!$A:$K,11,FALSE),"-") -> - | AE12: =IF(T12=AC12,"DEPOSITED","BELUM SETOR") -> DEPOSITED | AF12: =SUMIFS(statement!$I:$I,statement!$K:$K,ANALISA!$AA12, statement!$B:$B,ANALISA!AF$4) -> 0 | AG12: =SUMIFS(statement!$I:$I,statement!$K:$K,ANALISA!$AA12, statement!$B:$B,ANALISA!AG$4) -> 0 | AH12: =SUMIFS(statement!$I:$I,statement!$K:$K,ANALISA!$AA12, statement!$B:$B,ANALISA!AH$4) -> 0 | AI12: =SUMIFS(statement!$I:$I,statement!$K:$K,ANALISA!$AA12, statement!$B:$B,ANALISA!AI$4) -> 0 | AJ12: =SUMIFS(statement!$I:$I,statement!$K:$K,ANALISA!$AA12, statement!$B:$B,ANALISA!AJ$4) -> 0 | AK12: =SUMIFS(statement!$I:$I,statement!$K:$K,ANALISA!$AA12, statement!$B:$B,ANALISA!AK$4) -> 0 | AL12: =SUMIFS(statement!$I:$I,statement!$K:$K,ANALISA!$AA12, statement!$B:$B,ANALISA!AL$4) -> 0 | AM12: =SUMIFS(statement!$I:$I,statement!$K:$K,ANALISA!$AA12, statement!$B:$B,ANALISA!AM$4) -> 0 | ... AX12: =SUMIFS(statement!$I:$I,statement!$K:$K,ANALISA!$AA12, statement!$B:$B,ANALISA!AX$4) -> 0
A13: =C13 -> 46271 | B13: =TEXT(A13,"DD-MMM-YYYY DDDD") -> 06-Sep-2026 Sunday | C13: 46271 | D13: =SUMIF(statement!$K:$K,ANALISA!AA13,statement!$F:$F) -> 0 | E13: =SUMIFS(statement!$I:$I,statement!$K:$K,ANALISA!$AA13, statement!$B:$B,ANALISA!E$4) -> 0 | F13: =SUMIFS(statement!$H:$H,statement!$K:$K,ANALISA!$AA13, statement!$B:$B,ANALISA!F$4) -> 0 | G13: =SUMIFS(statement!$I:$I,statement!$K:$K,ANALISA!$AA13, statement!$B:$B,ANALISA!G$4) -> 0 | H13: =SUMIFS(statement!$I:$I,statement!$K:$K,ANALISA!$AA13, statement!$B:$B,ANALISA!H$4) -> 0 | I13: =SUMIFS(statement!$I:$I,statement!$K:$K,ANALISA!$AA13, statement!$B:$B,ANALISA!I$4) -> 0 | J13: =SUMIFS(statement!$I:$I,statement!$K:$K,ANALISA!$AA13, statement!$B:$B,ANALISA!J$4) -> 0 | K13: =SUMIFS(statement!$I:$I,statement!$K:$K,ANALISA!$AA13, statement!$B:$B,ANALISA!K$4) -> 0 | L13: =AF13+AG13+AH13+AI13+AJ13+AK13+AM13+AN13+AO13+AL13 -> 0 | M13: =SUMIFS(statement!$I:$I,statement!$K:$K,ANALISA!$AA13, statement!$B:$B,ANALISA!M$4) -> 0 | N13: =SUMIFS(statement!$I:$I,statement!$K:$K,ANALISA!$AA13, statement!$B:$B,ANALISA!N$4) -> 0 | O13: =SUMIFS(statement!$I:$I,statement!$K:$K,ANALISA!$AA13, statement!$B:$B,ANALISA!O$4) -> 0 | P13: =SUMIFS(statement!$I:$I,statement!$K:$K,ANALISA!$AA13, statement!$B:$B,ANALISA!P$4) -> 0 | Q13: =SUMIFS(statement!$I:$I,statement!$K:$K,ANALISA!$AA13, statement!$B:$B,ANALISA!Q$4) -> 0 | R13: =SUMIF(statement!$K:$K,ANALISA!AA13,statement!$J:$J) -> 0 | S13: =D13-G13-H13-I13-J13-N13-P13+R13-K13-L13-M13-O13 -> 0 | T13: =IFERROR(VLOOKUP(S13,RK!$D$1:$E$65536,1,FALSE),0) -> 0 | U13: =VLOOKUP(T13,RK!$D$1:$E$65536,2,FALSE) -> #N/A | W13: =VLOOKUP(V13,RK!$D$1:$E$65536,2,FALSE) -> #N/A | X13: =P13-S13+T13-V13 -> 0 | Y13: 0 | Z13: =Z12+S12-Y13 -> 0 | AA13: 6 | AC13: =S13 -> 0 | AD13: =IFERROR(VLOOKUP(AB13,BDEPO!$A:$K,11,FALSE),"-") -> - | AE13: =IF(T13=AC13,"DEPOSITED","BELUM SETOR") -> DEPOSITED | AF13: =SUMIFS(statement!$I:$I,statement!$K:$K,ANALISA!$AA13, statement!$B:$B,ANALISA!AF$4) -> 0 | AG13: =SUMIFS(statement!$I:$I,statement!$K:$K,ANALISA!$AA13, statement!$B:$B,ANALISA!AG$4) -> 0 | AH13: =SUMIFS(statement!$I:$I,statement!$K:$K,ANALISA!$AA13, statement!$B:$B,ANALISA!AH$4) -> 0 | AI13: =SUMIFS(statement!$I:$I,statement!$K:$K,ANALISA!$AA13, statement!$B:$B,ANALISA!AI$4) -> 0 | AJ13: =SUMIFS(statement!$I:$I,statement!$K:$K,ANALISA!$AA13, statement!$B:$B,ANALISA!AJ$4) -> 0 | AK13: =SUMIFS(statement!$I:$I,statement!$K:$K,ANALISA!$AA13, statement!$B:$B,ANALISA!AK$4) -> 0 | AL13: =SUMIFS(statement!$I:$I,statement!$K:$K,ANALISA!$AA13, statement!$B:$B,ANALISA!AL$4) -> 0 | AM13: =SUMIFS(statement!$I:$I,statement!$K:$K,ANALISA!$AA13, statement!$B:$B,ANALISA!AM$4) -> 0 | ... AX13: =SUMIFS(statement!$I:$I,statement!$K:$K,ANALISA!$AA13, statement!$B:$B,ANALISA!AX$4) -> 0
A14: =C14 -> 46272 | B14: =TEXT(A14,"DD-MMM-YYYY DDDD") -> 07-Sep-2026 Monday | C14: 46272 | D14: =SUMIF(statement!$K:$K,ANALISA!AA14,statement!$F:$F) -> 0 | E14: =SUMIFS(statement!$I:$I,statement!$K:$K,ANALISA!$AA14, statement!$B:$B,ANALISA!E$4) -> 0 | F14: =SUMIFS(statement!$H:$H,statement!$K:$K,ANALISA!$AA14, statement!$B:$B,ANALISA!F$4) -> 0 | G14: =SUMIFS(statement!$I:$I,statement!$K:$K,ANALISA!$AA14, statement!$B:$B,ANALISA!G$4) -> 0 | H14: =SUMIFS(statement!$I:$I,statement!$K:$K,ANALISA!$AA14, statement!$B:$B,ANALISA!H$4) -> 0 | I14: =SUMIFS(statement!$I:$I,statement!$K:$K,ANALISA!$AA14, statement!$B:$B,ANALISA!I$4) -> 0 | J14: =SUMIFS(statement!$I:$I,statement!$K:$K,ANALISA!$AA14, statement!$B:$B,ANALISA!J$4) -> 0 | K14: =SUMIFS(statement!$I:$I,statement!$K:$K,ANALISA!$AA14, statement!$B:$B,ANALISA!K$4) -> 0 | L14: =AF14+AG14+AH14+AI14+AJ14+AK14+AM14+AN14+AO14+AL14 -> 0 | M14: =SUMIFS(statement!$I:$I,statement!$K:$K,ANALISA!$AA14, statement!$B:$B,ANALISA!M$4) -> 0 | N14: =SUMIFS(statement!$I:$I,statement!$K:$K,ANALISA!$AA14, statement!$B:$B,ANALISA!N$4) -> 0 | O14: =SUMIFS(statement!$I:$I,statement!$K:$K,ANALISA!$AA14, statement!$B:$B,ANALISA!O$4) -> 0 | P14: =SUMIFS(statement!$I:$I,statement!$K:$K,ANALISA!$AA14, statement!$B:$B,ANALISA!P$4) -> 0 | Q14: =SUMIFS(statement!$I:$I,statement!$K:$K,ANALISA!$AA14, statement!$B:$B,ANALISA!Q$4) -> 0 | R14: =SUMIF(statement!$K:$K,ANALISA!AA14,statement!$J:$J) -> 0 | S14: =D14-G14-H14-I14-J14-N14-P14+R14-K14-L14-M14-O14 -> 0 | T14: =IFERROR(VLOOKUP(S14,RK!$D$1:$E$65536,1,FALSE),0) -> 0 | U14: =VLOOKUP(T14,RK!$D$1:$E$65536,2,FALSE) -> #N/A | W14: =VLOOKUP(V14,RK!$D$1:$E$65536,2,FALSE) -> #N/A | X14: =P14-S14+T14-V14 -> 0 | Y14: 0 | Z14: =Z13+S13-Y14 -> 0 | AA14: 7 | AC14: =S14 -> 0 | AD14: =IFERROR(VLOOKUP(AB14,BDEPO!$A:$K,11,FALSE),"-") -> - | AE14: =IF(T14=AC14,"DEPOSITED","BELUM SETOR") -> DEPOSITED | AF14: =SUMIFS(statement!$I:$I,statement!$K:$K,ANALISA!$AA14, statement!$B:$B,ANALISA!AF$4) -> 0 | AG14: =SUMIFS(statement!$I:$I,statement!$K:$K,ANALISA!$AA14, statement!$B:$B,ANALISA!AG$4) -> 0 | AH14: =SUMIFS(statement!$I:$I,statement!$K:$K,ANALISA!$AA14, statement!$B:$B,ANALISA!AH$4) -> 0 | AI14: =SUMIFS(statement!$I:$I,statement!$K:$K,ANALISA!$AA14, statement!$B:$B,ANALISA!AI$4) -> 0 | AJ14: =SUMIFS(statement!$I:$I,statement!$K:$K,ANALISA!$AA14, statement!$B:$B,ANALISA!AJ$4) -> 0 | AK14: =SUMIFS(statement!$I:$I,statement!$K:$K,ANALISA!$AA14, statement!$B:$B,ANALISA!AK$4) -> 0 | AL14: =SUMIFS(statement!$I:$I,statement!$K:$K,ANALISA!$AA14, statement!$B:$B,ANALISA!AL$4) -> 0 | AM14: =SUMIFS(statement!$I:$I,statement!$K:$K,ANALISA!$AA14, statement!$B:$B,ANALISA!AM$4) -> 0 | ... AX14: =SUMIFS(statement!$I:$I,statement!$K:$K,ANALISA!$AA14, statement!$B:$B,ANALISA!AX$4) -> 0
A15: =C15 -> 46273 | B15: =TEXT(A15,"DD-MMM-YYYY DDDD") -> 08-Sep-2026 Tuesday | C15: 46273 | D15: =SUMIF(statement!$K:$K,ANALISA!AA15,statement!$F:$F) -> 0 | E15: =SUMIFS(statement!$I:$I,statement!$K:$K,ANALISA!$AA15, statement!$B:$B,ANALISA!E$4) -> 0 | F15: =SUMIFS(statement!$H:$H,statement!$K:$K,ANALISA!$AA15, statement!$B:$B,ANALISA!F$4) -> 0 | G15: =SUMIFS(statement!$I:$I,statement!$K:$K,ANALISA!$AA15, statement!$B:$B,ANALISA!G$4) -> 0 | H15: =SUMIFS(statement!$I:$I,statement!$K:$K,ANALISA!$AA15, statement!$B:$B,ANALISA!H$4) -> 0 | I15: =SUMIFS(statement!$I:$I,statement!$K:$K,ANALISA!$AA15, statement!$B:$B,ANALISA!I$4) -> 0 | J15: =SUMIFS(statement!$I:$I,statement!$K:$K,ANALISA!$AA15, statement!$B:$B,ANALISA!J$4) -> 0 | K15: =SUMIFS(statement!$I:$I,statement!$K:$K,ANALISA!$AA15, statement!$B:$B,ANALISA!K$4) -> 0 | L15: =AF15+AG15+AH15+AI15+AJ15+AK15+AM15+AN15+AO15+AL15 -> 0 | M15: =SUMIFS(statement!$I:$I,statement!$K:$K,ANALISA!$AA15, statement!$B:$B,ANALISA!M$4) -> 0 | N15: =SUMIFS(statement!$I:$I,statement!$K:$K,ANALISA!$AA15, statement!$B:$B,ANALISA!N$4) -> 0 | O15: =SUMIFS(statement!$I:$I,statement!$K:$K,ANALISA!$AA15, statement!$B:$B,ANALISA!O$4) -> 0 | P15: =SUMIFS(statement!$I:$I,statement!$K:$K,ANALISA!$AA15, statement!$B:$B,ANALISA!P$4) -> 0 | Q15: =SUMIFS(statement!$I:$I,statement!$K:$K,ANALISA!$AA15, statement!$B:$B,ANALISA!Q$4) -> 0 | R15: =SUMIF(statement!$K:$K,ANALISA!AA15,statement!$J:$J) -> 0 | S15: =D15-G15-H15-I15-J15-N15-P15+R15-K15-L15-M15-O15 -> 0 | T15: =IFERROR(VLOOKUP(S15,RK!$D$1:$E$65536,1,FALSE),0) -> 0 | U15: =VLOOKUP(T15,RK!$D$1:$E$65536,2,FALSE) -> #N/A | W15: =VLOOKUP(V15,RK!$D$1:$E$65536,2,FALSE) -> #N/A | X15: =P15-S15+T15-V15 -> 0 | Y15: 0 | Z15: =Z14+S14-Y15 -> 0 | AA15: 8 | AC15: =S15 -> 0 | AD15: =IFERROR(VLOOKUP(AB15,BDEPO!$A:$K,11,FALSE),"-") -> - | AE15: =IF(T15=AC15,"DEPOSITED","BELUM SETOR") -> DEPOSITED | AF15: =SUMIFS(statement!$I:$I,statement!$K:$K,ANALISA!$AA15, statement!$B:$B,ANALISA!AF$4) -> 0 | AG15: =SUMIFS(statement!$I:$I,statement!$K:$K,ANALISA!$AA15, statement!$B:$B,ANALISA!AG$4) -> 0 | AH15: =SUMIFS(statement!$I:$I,statement!$K:$K,ANALISA!$AA15, statement!$B:$B,ANALISA!AH$4) -> 0 | AI15: =SUMIFS(statement!$I:$I,statement!$K:$K,ANALISA!$AA15, statement!$B:$B,ANALISA!AI$4) -> 0 | AJ15: =SUMIFS(statement!$I:$I,statement!$K:$K,ANALISA!$AA15, statement!$B:$B,ANALISA!AJ$4) -> 0 | AK15: =SUMIFS(statement!$I:$I,statement!$K:$K,ANALISA!$AA15, statement!$B:$B,ANALISA!AK$4) -> 0 | AL15: =SUMIFS(statement!$I:$I,statement!$K:$K,ANALISA!$AA15, statement!$B:$B,ANALISA!AL$4) -> 0 | AM15: =SUMIFS(statement!$I:$I,statement!$K:$K,ANALISA!$AA15, statement!$B:$B,ANALISA!AM$4) -> 0 | ... AX15: =SUMIFS(statement!$I:$I,statement!$K:$K,ANALISA!$AA15, statement!$B:$B,ANALISA!AX$4) -> 0
A16: =C16 -> 46274 | B16: =TEXT(A16,"DD-MMM-YYYY DDDD") -> 09-Sep-2026 Wednesday | C16: 46274 | D16: =SUMIF(statement!$K:$K,ANALISA!AA16,statement!$F:$F) -> 0 | E16: =SUMIFS(statement!$I:$I,statement!$K:$K,ANALISA!$AA16, statement!$B:$B,ANALISA!E$4) -> 0 | F16: =SUMIFS(statement!$H:$H,statement!$K:$K,ANALISA!$AA16, statement!$B:$B,ANALISA!F$4) -> 0 | G16: =SUMIFS(statement!$I:$I,statement!$K:$K,ANALISA!$AA16, statement!$B:$B,ANALISA!G$4) -> 0 | H16: =SUMIFS(statement!$I:$I,statement!$K:$K,ANALISA!$AA16, statement!$B:$B,ANALISA!H$4) -> 0 | I16: =SUMIFS(statement!$I:$I,statement!$K:$K,ANALISA!$AA16, statement!$B:$B,ANALISA!I$4) -> 0 | J16: =SUMIFS(statement!$I:$I,statement!$K:$K,ANALISA!$AA16, statement!$B:$B,ANALISA!J$4) -> 0 | K16: =SUMIFS(statement!$I:$I,statement!$K:$K,ANALISA!$AA16, statement!$B:$B,ANALISA!K$4) -> 0 | L16: =AF16+AG16+AH16+AI16+AJ16+AK16+AM16+AN16+AO16+AL16 -> 0 | M16: =SUMIFS(statement!$I:$I,statement!$K:$K,ANALISA!$AA16, statement!$B:$B,ANALISA!M$4) -> 0 | N16: =SUMIFS(statement!$I:$I,statement!$K:$K,ANALISA!$AA16, statement!$B:$B,ANALISA!N$4) -> 0 | O16: =SUMIFS(statement!$I:$I,statement!$K:$K,ANALISA!$AA16, statement!$B:$B,ANALISA!O$4) -> 0 | P16: =SUMIFS(statement!$I:$I,statement!$K:$K,ANALISA!$AA16, statement!$B:$B,ANALISA!P$4) -> 0 | Q16: =SUMIFS(statement!$I:$I,statement!$K:$K,ANALISA!$AA16, statement!$B:$B,ANALISA!Q$4) -> 0 | R16: =SUMIF(statement!$K:$K,ANALISA!AA16,statement!$J:$J) -> 0 | S16: =D16-G16-H16-I16-J16-N16-P16+R16-K16-L16-M16-O16 -> 0 | T16: =IFERROR(VLOOKUP(S16,RK!$D$1:$E$65536,1,FALSE),0) -> 0 | U16: =VLOOKUP(T16,RK!$D$1:$E$65536,2,FALSE) -> #N/A | W16: =VLOOKUP(V16,RK!$D$1:$E$65536,2,FALSE) -> #N/A | X16: =P16-S16+T16-V16 -> 0 | Y16: 0 | Z16: =Z15+S15-Y16 -> 0 | AA16: 9 | AC16: =S16 -> 0 | AD16: =IFERROR(VLOOKUP(AB16,BDEPO!$A:$K,11,FALSE),"-") -> - | AE16: =IF(T16=AC16,"DEPOSITED","BELUM SETOR") -> DEPOSITED | AF16: =SUMIFS(statement!$I:$I,statement!$K:$K,ANALISA!$AA16, statement!$B:$B,ANALISA!AF$4) -> 0 | AG16: =SUMIFS(statement!$I:$I,statement!$K:$K,ANALISA!$AA16, statement!$B:$B,ANALISA!AG$4) -> 0 | AH16: =SUMIFS(statement!$I:$I,statement!$K:$K,ANALISA!$AA16, statement!$B:$B,ANALISA!AH$4) -> 0 | AI16: =SUMIFS(statement!$I:$I,statement!$K:$K,ANALISA!$AA16, statement!$B:$B,ANALISA!AI$4) -> 0 | AJ16: =SUMIFS(statement!$I:$I,statement!$K:$K,ANALISA!$AA16, statement!$B:$B,ANALISA!AJ$4) -> 0 | AK16: =SUMIFS(statement!$I:$I,statement!$K:$K,ANALISA!$AA16, statement!$B:$B,ANALISA!AK$4) -> 0 | AL16: =SUMIFS(statement!$I:$I,statement!$K:$K,ANALISA!$AA16, statement!$B:$B,ANALISA!AL$4) -> 0 | AM16: =SUMIFS(statement!$I:$I,statement!$K:$K,ANALISA!$AA16, statement!$B:$B,ANALISA!AM$4) -> 0 | ... AX16: =SUMIFS(statement!$I:$I,statement!$K:$K,ANALISA!$AA16, statement!$B:$B,ANALISA!AX$4) -> 0
A17: =C17 -> 46275 | B17: =TEXT(A17,"DD-MMM-YYYY DDDD") -> 10-Sep-2026 Thursday | C17: 46275 | D17: =SUMIF(statement!$K:$K,ANALISA!AA17,statement!$F:$F) -> 0 | E17: =SUMIFS(statement!$I:$I,statement!$K:$K,ANALISA!$AA17, statement!$B:$B,ANALISA!E$4) -> 0 | F17: =SUMIFS(statement!$H:$H,statement!$K:$K,ANALISA!$AA17, statement!$B:$B,ANALISA!F$4) -> 0 | G17: =SUMIFS(statement!$I:$I,statement!$K:$K,ANALISA!$AA17, statement!$B:$B,ANALISA!G$4) -> 0 | H17: =SUMIFS(statement!$I:$I,statement!$K:$K,ANALISA!$AA17, statement!$B:$B,ANALISA!H$4) -> 0 | I17: =SUMIFS(statement!$I:$I,statement!$K:$K,ANALISA!$AA17, statement!$B:$B,ANALISA!I$4) -> 0 | J17: =SUMIFS(statement!$I:$I,statement!$K:$K,ANALISA!$AA17, statement!$B:$B,ANALISA!J$4) -> 0 | K17: =SUMIFS(statement!$I:$I,statement!$K:$K,ANALISA!$AA17, statement!$B:$B,ANALISA!K$4) -> 0 | L17: =AF17+AG17+AH17+AI17+AJ17+AK17+AM17+AN17+AO17+AL17 -> 0 | M17: =SUMIFS(statement!$I:$I,statement!$K:$K,ANALISA!$AA17, statement!$B:$B,ANALISA!M$4) -> 0 | N17: =SUMIFS(statement!$I:$I,statement!$K:$K,ANALISA!$AA17, statement!$B:$B,ANALISA!N$4) -> 0 | O17: =SUMIFS(statement!$I:$I,statement!$K:$K,ANALISA!$AA17, statement!$B:$B,ANALISA!O$4) -> 0 | P17: =SUMIFS(statement!$I:$I,statement!$K:$K,ANALISA!$AA17, statement!$B:$B,ANALISA!P$4) -> 0 | Q17: =SUMIFS(statement!$I:$I,statement!$K:$K,ANALISA!$AA17, statement!$B:$B,ANALISA!Q$4) -> 0 | R17: =SUMIF(statement!$K:$K,ANALISA!AA17,statement!$J:$J) -> 0 | S17: =D17-G17-H17-I17-J17-N17-P17+R17-K17-L17-M17-O17 -> 0 | T17: =IFERROR(VLOOKUP(S17,RK!$D$1:$E$65536,1,FALSE),0) -> 0 | U17: =VLOOKUP(T17,RK!$D$1:$E$65536,2,FALSE) -> #N/A | W17: =VLOOKUP(V17,RK!$D$1:$E$65536,2,FALSE) -> #N/A | X17: =P17-S17+T17-V17 -> 0 | Y17: 0 | Z17: =Z16+S16-Y17 -> 0 | AA17: 10 | AC17: =S17 -> 0 | AD17: =IFERROR(VLOOKUP(AB17,BDEPO!$A:$K,11,FALSE),"-") -> - | AE17: =IF(T17=AC17,"DEPOSITED","BELUM SETOR") -> DEPOSITED | AF17: =SUMIFS(statement!$I:$I,statement!$K:$K,ANALISA!$AA17, statement!$B:$B,ANALISA!AF$4) -> 0 | AG17: =SUMIFS(statement!$I:$I,statement!$K:$K,ANALISA!$AA17, statement!$B:$B,ANALISA!AG$4) -> 0 | AH17: =SUMIFS(statement!$I:$I,statement!$K:$K,ANALISA!$AA17, statement!$B:$B,ANALISA!AH$4) -> 0 | AI17: =SUMIFS(statement!$I:$I,statement!$K:$K,ANALISA!$AA17, statement!$B:$B,ANALISA!AI$4) -> 0 | AJ17: =SUMIFS(statement!$I:$I,statement!$K:$K,ANALISA!$AA17, statement!$B:$B,ANALISA!AJ$4) -> 0 | AK17: =SUMIFS(statement!$I:$I,statement!$K:$K,ANALISA!$AA17, statement!$B:$B,ANALISA!AK$4) -> 0 | AL17: =SUMIFS(statement!$I:$I,statement!$K:$K,ANALISA!$AA17, statement!$B:$B,ANALISA!AL$4) -> 0 | AM17: =SUMIFS(statement!$I:$I,statement!$K:$K,ANALISA!$AA17, statement!$B:$B,ANALISA!AM$4) -> 0 | ... AX17: =SUMIFS(statement!$I:$I,statement!$K:$K,ANALISA!$AA17, statement!$B:$B,ANALISA!AX$4) -> 0
A18: =C18 -> 46276 | B18: =TEXT(A18,"DD-MMM-YYYY DDDD") -> 11-Sep-2026 Friday | C18: 46276 | D18: =SUMIF(statement!$K:$K,ANALISA!AA18,statement!$F:$F) -> 0 | E18: =SUMIFS(statement!$I:$I,statement!$K:$K,ANALISA!$AA18, statement!$B:$B,ANALISA!E$4) -> 0 | F18: =SUMIFS(statement!$H:$H,statement!$K:$K,ANALISA!$AA18, statement!$B:$B,ANALISA!F$4) -> 0 | G18: =SUMIFS(statement!$I:$I,statement!$K:$K,ANALISA!$AA18, statement!$B:$B,ANALISA!G$4) -> 0 | H18: =SUMIFS(statement!$I:$I,statement!$K:$K,ANALISA!$AA18, statement!$B:$B,ANALISA!H$4) -> 0 | I18: =SUMIFS(statement!$I:$I,statement!$K:$K,ANALISA!$AA18, statement!$B:$B,ANALISA!I$4) -> 0 | J18: =SUMIFS(statement!$I:$I,statement!$K:$K,ANALISA!$AA18, statement!$B:$B,ANALISA!J$4) -> 0 | K18: =SUMIFS(statement!$I:$I,statement!$K:$K,ANALISA!$AA18, statement!$B:$B,ANALISA!K$4) -> 0 | L18: =AF18+AG18+AH18+AI18+AJ18+AK18+AM18+AN18+AO18+AL18 -> 0 | M18: =SUMIFS(statement!$I:$I,statement!$K:$K,ANALISA!$AA18, statement!$B:$B,ANALISA!M$4) -> 0 | N18: =SUMIFS(statement!$I:$I,statement!$K:$K,ANALISA!$AA18, statement!$B:$B,ANALISA!N$4) -> 0 | O18: =SUMIFS(statement!$I:$I,statement!$K:$K,ANALISA!$AA18, statement!$B:$B,ANALISA!O$4) -> 0 | P18: =SUMIFS(statement!$I:$I,statement!$K:$K,ANALISA!$AA18, statement!$B:$B,ANALISA!P$4) -> 0 | Q18: =SUMIFS(statement!$I:$I,statement!$K:$K,ANALISA!$AA18, statement!$B:$B,ANALISA!Q$4) -> 0 | R18: =SUMIF(statement!$K:$K,ANALISA!AA18,statement!$J:$J) -> 0 | S18: =D18-G18-H18-I18-J18-N18-P18+R18-K18-L18-M18-O18 -> 0 | T18: =IFERROR(VLOOKUP(S18,RK!$D$1:$E$65536,1,FALSE),0) -> 0 | U18: =VLOOKUP(T18,RK!$D$1:$E$65536,2,FALSE) -> #N/A | W18: =VLOOKUP(V18,RK!$D$1:$E$65536,2,FALSE) -> #N/A | X18: =P18-S18+T18-V18 -> 0 | Y18: 0 | Z18: =Z17+S17-Y18 -> 0 | AA18: 11 | AC18: =S18 -> 0 | AD18: =IFERROR(VLOOKUP(AB18,BDEPO!$A:$K,11,FALSE),"-") -> - | AE18: =IF(T18=AC18,"DEPOSITED","BELUM SETOR") -> DEPOSITED | AF18: =SUMIFS(statement!$I:$I,statement!$K:$K,ANALISA!$AA18, statement!$B:$B,ANALISA!AF$4) -> 0 | AG18: =SUMIFS(statement!$I:$I,statement!$K:$K,ANALISA!$AA18, statement!$B:$B,ANALISA!AG$4) -> 0 | AH18: =SUMIFS(statement!$I:$I,statement!$K:$K,ANALISA!$AA18, statement!$B:$B,ANALISA!AH$4) -> 0 | AI18: =SUMIFS(statement!$I:$I,statement!$K:$K,ANALISA!$AA18, statement!$B:$B,ANALISA!AI$4) -> 0 | AJ18: =SUMIFS(statement!$I:$I,statement!$K:$K,ANALISA!$AA18, statement!$B:$B,ANALISA!AJ$4) -> 0 | AK18: =SUMIFS(statement!$I:$I,statement!$K:$K,ANALISA!$AA18, statement!$B:$B,ANALISA!AK$4) -> 0 | AL18: =SUMIFS(statement!$I:$I,statement!$K:$K,ANALISA!$AA18, statement!$B:$B,ANALISA!AL$4) -> 0 | AM18: =SUMIFS(statement!$I:$I,statement!$K:$K,ANALISA!$AA18, statement!$B:$B,ANALISA!AM$4) -> 0 | ... AX18: =SUMIFS(statement!$I:$I,statement!$K:$K,ANALISA!$AA18, statement!$B:$B,ANALISA!AX$4) -> 0
A19: =C19 -> 46277 | B19: =TEXT(A19,"DD-MMM-YYYY DDDD") -> 12-Sep-2026 Saturday | C19: 46277 | D19: =SUMIF(statement!$K:$K,ANALISA!AA19,statement!$F:$F) -> 0 | E19: =SUMIFS(statement!$I:$I,statement!$K:$K,ANALISA!$AA19, statement!$B:$B,ANALISA!E$4) -> 0 | F19: =SUMIFS(statement!$H:$H,statement!$K:$K,ANALISA!$AA19, statement!$B:$B,ANALISA!F$4) -> 0 | G19: =SUMIFS(statement!$I:$I,statement!$K:$K,ANALISA!$AA19, statement!$B:$B,ANALISA!G$4) -> 0 | H19: =SUMIFS(statement!$I:$I,statement!$K:$K,ANALISA!$AA19, statement!$B:$B,ANALISA!H$4) -> 0 | I19: =SUMIFS(statement!$I:$I,statement!$K:$K,ANALISA!$AA19, statement!$B:$B,ANALISA!I$4) -> 0 | J19: =SUMIFS(statement!$I:$I,statement!$K:$K,ANALISA!$AA19, statement!$B:$B,ANALISA!J$4) -> 0 | K19: =SUMIFS(statement!$I:$I,statement!$K:$K,ANALISA!$AA19, statement!$B:$B,ANALISA!K$4) -> 0 | L19: =AF19+AG19+AH19+AI19+AJ19+AK19+AM19+AN19+AO19+AL19 -> 0 | M19: =SUMIFS(statement!$I:$I,statement!$K:$K,ANALISA!$AA19, statement!$B:$B,ANALISA!M$4) -> 0 | N19: =SUMIFS(statement!$I:$I,statement!$K:$K,ANALISA!$AA19, statement!$B:$B,ANALISA!N$4) -> 0 | O19: =SUMIFS(statement!$I:$I,statement!$K:$K,ANALISA!$AA19, statement!$B:$B,ANALISA!O$4) -> 0 | P19: =SUMIFS(statement!$I:$I,statement!$K:$K,ANALISA!$AA19, statement!$B:$B,ANALISA!P$4) -> 0 | Q19: =SUMIFS(statement!$I:$I,statement!$K:$K,ANALISA!$AA19, statement!$B:$B,ANALISA!Q$4) -> 0 | R19: =SUMIF(statement!$K:$K,ANALISA!AA19,statement!$J:$J) -> 0 | S19: =D19-G19-H19-I19-J19-N19-P19+R19-K19-L19-M19-O19 -> 0 | T19: =IFERROR(VLOOKUP(S19,RK!$D$1:$E$65536,1,FALSE),0) -> 0 | U19: =VLOOKUP(T19,RK!$D$1:$E$65536,2,FALSE) -> #N/A | W19: =VLOOKUP(V19,RK!$D$1:$E$65536,2,FALSE) -> #N/A | X19: =P19-S19+T19-V19 -> 0 | Y19: 0 | Z19: =Z18+S18-Y19 -> 0 | AA19: 12 | AC19: =S19 -> 0 | AD19: =IFERROR(VLOOKUP(AB19,BDEPO!$A:$K,11,FALSE),"-") -> - | AE19: =IF(T19=AC19,"DEPOSITED","BELUM SETOR") -> DEPOSITED | AF19: =SUMIFS(statement!$I:$I,statement!$K:$K,ANALISA!$AA19, statement!$B:$B,ANALISA!AF$4) -> 0 | AG19: =SUMIFS(statement!$I:$I,statement!$K:$K,ANALISA!$AA19, statement!$B:$B,ANALISA!AG$4) -> 0 | AH19: =SUMIFS(statement!$I:$I,statement!$K:$K,ANALISA!$AA19, statement!$B:$B,ANALISA!AH$4) -> 0 | AI19: =SUMIFS(statement!$I:$I,statement!$K:$K,ANALISA!$AA19, statement!$B:$B,ANALISA!AI$4) -> 0 | AJ19: =SUMIFS(statement!$I:$I,statement!$K:$K,ANALISA!$AA19, statement!$B:$B,ANALISA!AJ$4) -> 0 | AK19: =SUMIFS(statement!$I:$I,statement!$K:$K,ANALISA!$AA19, statement!$B:$B,ANALISA!AK$4) -> 0 | AL19: =SUMIFS(statement!$I:$I,statement!$K:$K,ANALISA!$AA19, statement!$B:$B,ANALISA!AL$4) -> 0 | AM19: =SUMIFS(statement!$I:$I,statement!$K:$K,ANALISA!$AA19, statement!$B:$B,ANALISA!AM$4) -> 0 | ... AX19: =SUMIFS(statement!$I:$I,statement!$K:$K,ANALISA!$AA19, statement!$B:$B,ANALISA!AX$4) -> 0
A20: =C20 -> 46278 | B20: =TEXT(A20,"DD-MMM-YYYY DDDD") -> 13-Sep-2026 Sunday | C20: 46278 | D20: =SUMIF(statement!$K:$K,ANALISA!AA20,statement!$F:$F) -> 0 | E20: =SUMIFS(statement!$I:$I,statement!$K:$K,ANALISA!$AA20, statement!$B:$B,ANALISA!E$4) -> 0 | F20: =SUMIFS(statement!$H:$H,statement!$K:$K,ANALISA!$AA20, statement!$B:$B,ANALISA!F$4) -> 0 | G20: =SUMIFS(statement!$I:$I,statement!$K:$K,ANALISA!$AA20, statement!$B:$B,ANALISA!G$4) -> 0 | H20: =SUMIFS(statement!$I:$I,statement!$K:$K,ANALISA!$AA20, statement!$B:$B,ANALISA!H$4) -> 0 | I20: =SUMIFS(statement!$I:$I,statement!$K:$K,ANALISA!$AA20, statement!$B:$B,ANALISA!I$4) -> 0 | J20: =SUMIFS(statement!$I:$I,statement!$K:$K,ANALISA!$AA20, statement!$B:$B,ANALISA!J$4) -> 0 | K20: =SUMIFS(statement!$I:$I,statement!$K:$K,ANALISA!$AA20, statement!$B:$B,ANALISA!K$4) -> 0 | L20: =AF20+AG20+AH20+AI20+AJ20+AK20+AM20+AN20+AO20+AL20 -> 0 | M20: =SUMIFS(statement!$I:$I,statement!$K:$K,ANALISA!$AA20, statement!$B:$B,ANALISA!M$4) -> 0 | N20: =SUMIFS(statement!$I:$I,statement!$K:$K,ANALISA!$AA20, statement!$B:$B,ANALISA!N$4) -> 0 | O20: =SUMIFS(statement!$I:$I,statement!$K:$K,ANALISA!$AA20, statement!$B:$B,ANALISA!O$4) -> 0 | P20: =SUMIFS(statement!$I:$I,statement!$K:$K,ANALISA!$AA20, statement!$B:$B,ANALISA!P$4) -> 0 | Q20: =SUMIFS(statement!$I:$I,statement!$K:$K,ANALISA!$AA20, statement!$B:$B,ANALISA!Q$4) -> 0 | R20: =SUMIF(statement!$K:$K,ANALISA!AA20,statement!$J:$J) -> 0 | S20: =D20-G20-H20-I20-J20-N20-P20+R20-K20-L20-M20-O20 -> 0 | T20: =IFERROR(VLOOKUP(S20,RK!$D$1:$E$65536,1,FALSE),0) -> 0 | U20: =VLOOKUP(T20,RK!$D$1:$E$65536,2,FALSE) -> #N/A | W20: =VLOOKUP(V20,RK!$D$1:$E$65536,2,FALSE) -> #N/A | X20: =P20-S20+T20-V20 -> 0 | Y20: 0 | Z20: =Z19+S19-Y20 -> 0 | AA20: 13 | AC20: =S20 -> 0 | AD20: =IFERROR(VLOOKUP(AB20,BDEPO!$A:$K,11,FALSE),"-") -> - | AE20: =IF(T20=AC20,"DEPOSITED","BELUM SETOR") -> DEPOSITED | AF20: =SUMIFS(statement!$I:$I,statement!$K:$K,ANALISA!$AA20, statement!$B:$B,ANALISA!AF$4) -> 0 | AG20: =SUMIFS(statement!$I:$I,statement!$K:$K,ANALISA!$AA20, statement!$B:$B,ANALISA!AG$4) -> 0 | AH20: =SUMIFS(statement!$I:$I,statement!$K:$K,ANALISA!$AA20, statement!$B:$B,ANALISA!AH$4) -> 0 | AI20: =SUMIFS(statement!$I:$I,statement!$K:$K,ANALISA!$AA20, statement!$B:$B,ANALISA!AI$4) -> 0 | AJ20: =SUMIFS(statement!$I:$I,statement!$K:$K,ANALISA!$AA20, statement!$B:$B,ANALISA!AJ$4) -> 0 | AK20: =SUMIFS(statement!$I:$I,statement!$K:$K,ANALISA!$AA20, statement!$B:$B,ANALISA!AK$4) -> 0 | AL20: =SUMIFS(statement!$I:$I,statement!$K:$K,ANALISA!$AA20, statement!$B:$B,ANALISA!AL$4) -> 0 | AM20: =SUMIFS(statement!$I:$I,statement!$K:$K,ANALISA!$AA20, statement!$B:$B,ANALISA!AM$4) -> 0 | ... AX20: =SUMIFS(statement!$I:$I,statement!$K:$K,ANALISA!$AA20, statement!$B:$B,ANALISA!AX$4) -> 0
... A38: =C38 -> 46296 | B38: =TEXT(A38,"DD-MMM-YYYY DDDD") -> 01-Oct-2026 Thursday | C38: 46296 | D38: =SUMIF(statement!$K:$K,ANALISA!AA38,statement!$F:$F) -> 0 | E38: =SUMIFS(statement!$I:$I,statement!$K:$K,ANALISA!$AA38, statement!$B:$B,ANALISA!E$4) -> 0 | F38: =SUMIFS(statement!$H:$H,statement!$K:$K,ANALISA!$AA38, statement!$B:$B,ANALISA!F$4) -> 0 | G38: =SUMIFS(statement!$I:$I,statement!$K:$K,ANALISA!$AA38, statement!$B:$B,ANALISA!G$4) -> 0 | H38: =SUMIFS(statement!$I:$I,statement!$K:$K,ANALISA!$AA38, statement!$B:$B,ANALISA!H$4) -> 0 | I38: =SUMIFS(statement!$I:$I,statement!$K:$K,ANALISA!$AA38, statement!$B:$B,ANALISA!I$4) -> 0 | J38: =SUMIFS(statement!$I:$I,statement!$K:$K,ANALISA!$AA38, statement!$B:$B,ANALISA!J$4) -> 0 | K38: =SUMIFS(statement!$I:$I,statement!$K:$K,ANALISA!$AA38, statement!$B:$B,ANALISA!K$4) -> 0 | L38: =AF38+AG38+AH38+AI38+AJ38+AK38+AM38+AN38+AO38+AL38 -> 0 | M38: =SUMIFS(statement!$I:$I,statement!$K:$K,ANALISA!$AA38, statement!$B:$B,ANALISA!M$4) -> 0 | N38: =SUMIFS(statement!$I:$I,statement!$K:$K,ANALISA!$AA38, statement!$B:$B,ANALISA!N$4) -> 0 | O38: =SUMIFS(statement!$I:$I,statement!$K:$K,ANALISA!$AA38, statement!$B:$B,ANALISA!O$4) -> 0 | P38: =SUMIFS(statement!$I:$I,statement!$K:$K,ANALISA!$AA38, statement!$B:$B,ANALISA!P$4) -> 0 | Q38: =SUMIFS(statement!$I:$I,statement!$K:$K,ANALISA!$AA38, statement!$B:$B,ANALISA!Q$4) -> 0 | R38: =SUMIF(statement!$K:$K,ANALISA!AA38,statement!$J:$J) -> 0 | S38: =D38-G38-H38-I38-J38-N38-P38+R38-K38-L38-M38-O38 -> 0 | T38: =IFERROR(VLOOKUP(S38,RK!$D$1:$E$65536,1,FALSE),0) -> 0 | U38: =VLOOKUP(T38,RK!$D$1:$E$65536,2,FALSE) -> #N/A | W38: =VLOOKUP(V38,RK!$D$1:$E$65536,2,FALSE) -> #N/A | X38: =P38-S38+T38-V38 -> 0 | Y38: 0 | Z38: =Z37+S37-Y38 -> 0 | AA38: 31 | AC38: =S38 -> 0 | AD38: =IFERROR(VLOOKUP(AB38,BDEPO!$A:$K,11,FALSE),"-") -> - | AE38: =IF(T38=AC38,"DEPOSITED","BELUM SETOR") -> DEPOSITED | AF38: =SUMIFS(statement!$I:$I,statement!$K:$K,ANALISA!$AA38, statement!$B:$B,ANALISA!AF$4) -> 0 | AG38: =SUMIFS(statement!$I:$I,statement!$K:$K,ANALISA!$AA38, statement!$B:$B,ANALISA!AG$4) -> 0 | AH38: =SUMIFS(statement!$I:$I,statement!$K:$K,ANALISA!$AA38, statement!$B:$B,ANALISA!AH$4) -> 0 | AI38: =SUMIFS(statement!$I:$I,statement!$K:$K,ANALISA!$AA38, statement!$B:$B,ANALISA!AI$4) -> 0 | AJ38: =SUMIFS(statement!$I:$I,statement!$K:$K,ANALISA!$AA38, statement!$B:$B,ANALISA!AJ$4) -> 0 | AK38: =SUMIFS(statement!$I:$I,statement!$K:$K,ANALISA!$AA38, statement!$B:$B,ANALISA!AK$4) -> 0 | AL38: =SUMIFS(statement!$I:$I,statement!$K:$K,ANALISA!$AA38, statement!$B:$B,ANALISA!AL$4) -> 0 | AM38: =SUMIFS(statement!$I:$I,statement!$K:$K,ANALISA!$AA38, statement!$B:$B,ANALISA!AM$4) -> 0 | ... AX38: =SUMIFS(statement!$I:$I,statement!$K:$K,ANALISA!$AA38, statement!$B:$B,ANALISA!AX$4) -> 0
Z39: =Z38+S38-Y39 -> 0
C40: TOTAL | D40: =SUM(D8:D38) -> 0 | E40: =SUM(E8:E38) -> 0 | F40: =SUM(F8:F38) -> 0 | G40: =SUM(G8:G38) -> 0 | H40: =SUM(H8:H38) -> 0 | I40: =SUM(I8:I38) -> 0 | J40: =SUM(J8:J38) -> 0 | K40: =SUM(K8:K38) -> 0 | ... N40: =SUM(N8:N38) -> 0 | P40: =SUM(P8:P38) -> 0 | Q40: =SUM(Q8:Q38) -> 0 | R40: =SUM(R8:R38) -> 0 | S40: =SUM(S8:S38) -> 0 | T40: =SUM(T8:T38) -> 0 | U40: =SUM(U8:U38) -> #N/A | V40: =SUM(V8:V38) -> 0 | W40: =SUM(W8:W38) -> #N/A | X40: =SUM(X8:X38) -> 0 | Y40: 0 | Z40: =Z39+S39-Y40 -> 0
C41: Rata-rata | D41: =+D40/30 -> 0 | E41: =+E40/30 -> 0 | F41: =+F40/30 -> 0 | G41: =+G40/30 -> 0 | H41: =+H40/30 -> 0 | I41: =+I40/30 -> 0 | J41: =+J40/30 -> 0 | K41: =+K40/30 -> 0 | ... N41: =+N40/30 -> 0 | P41: =+P40/30 -> 0 | Q41: =+Q40/30 -> 0 | R41: =+R40/30 -> 0 | S41: =+S40/30 -> 0 | T41: =+T40/30 -> 0 | U41: =+U40/30 -> #N/A | V41: =+V40/30 -> 0 | W41: =+W40/30 -> #N/A | X41: =+X40/30 -> 0 | Y41: 0 | Z41: =Z40+S40-Y41 -> 0
C43: Omzet Bank In | D43: =T40 -> 0
C44: Omzet AX | D44: =S40 -> 0
C45: Selisih | D45: =SUM(D44-D43) -> 0

Sheet NIK KASIR
A1: Susun NIK Kasir di Kolom A

Sheet INCOME EXPENSE

Sheet SHORTAGE
B1: =ANALISA!C1 -> GRAMEDIA
B2: CASHIER SHORTAGE
B3: =ANALISA!C2 -> REKONSILIASI OMSET BULAN :
B6: NIK CASHIER | C6: ='NIK KASIR'!$A2 -> 0 | D6: ='NIK KASIR'!$A3 -> 0 | E6: ='NIK KASIR'!$A4 -> 0 | F6: ='NIK KASIR'!$A5 -> 0 | G6: ='NIK KASIR'!$A6 -> 0 | H6: ='NIK KASIR'!$A7 -> 0 | I6: ='NIK KASIR'!$A8 -> 0 | J6: ='NIK KASIR'!$A9 -> 0 | K6: ='NIK KASIR'!$A10 -> 0 | L6: ='NIK KASIR'!$A11 -> 0 | M6: ='NIK KASIR'!$A12 -> 0 | N6: ='NIK KASIR'!$A13 -> 0 | O6: ='NIK KASIR'!$A14 -> 0 | P6: ='NIK KASIR'!$A15 -> 0 | Q6: ='NIK KASIR'!$A16 -> 0 | R6: ='NIK KASIR'!$A17 -> 0 | S6: ='NIK KASIR'!$A18 -> 0 | T6: ='NIK KASIR'!$A19 -> 0 | U6: ='NIK KASIR'!$A20 -> 0 | V6: ='NIK KASIR'!$A21 -> 0 | W6: ='NIK KASIR'!$A22 -> 0 | X6: ='NIK KASIR'!$A23 -> 0 | Y6: ='NIK KASIR'!$A24 -> 0 | Z6: ='NIK KASIR'!$A25 -> 0 | AA6: ='NIK KASIR'!$A26 -> 0 | AB6: ='NIK KASIR'!$A27 -> 0 | AC6: ='NIK KASIR'!$A28 -> 0 | AD6: ='NIK KASIR'!$A29 -> 0 | AE6: ='NIK KASIR'!$A30 -> 0 | AF6: ='NIK KASIR'!$A31 -> 0 | AG6: ='NIK KASIR'!$A32 -> 0 | AH6: ='NIK KASIR'!$A33 -> 0 | AI6: ='NIK KASIR'!$A34 -> 0 | AJ6: STATEMENT NUMBER | AK6: TOTAL | AL6: CHECK
C7: Cashier 1 | D7: Cashier 2 | E7: Cashier 3 | F7: Cashier 4 | G7: Cashier 5 | H7: Cashier 6 | I7: Cashier 7 | J7: Cashier 8 | K7: Cashier 9 | L7: Cashier 10 | M7: Cashier 11 | N7: Cashier 12 | O7: Cashier 13 | P7: Cashier 14 | Q7: Cashier 15 | R7: Cashier 16 | S7: Cashier 17 | T7: Cashier 18 | U7: Cashier 19 | V7: Cashier 20 | W7: Cashier 21 | X7: Cashier 22 | Y7: Cashier 23 | Z7: Cashier 24 | AA7: Cashier 25 | AB7: Cashier 26 | AC7: Cashier 27 | AD7: Cashier 28 | AE7: Cashier 29 | AF7: Cashier 30 | AG7: Cashier 31 | AH7: Cashier 32 | AI7: Cashier 33
B8: NAME CASHIER | C8: =IF(ISERROR(VLOOKUP(C6,KARY!$B$1:$C$62016,2,FALSE)),0,(VLOOKUP(C6,KARY!$B$1:$C$62016,2,FALSE))) -> 0 | D8: =IF(ISERROR(VLOOKUP(D6,KARY!$B$1:$C$62016,2,FALSE)),0,(VLOOKUP(D6,KARY!$B$1:$C$62016,2,FALSE))) -> 0 | E8: =IF(ISERROR(VLOOKUP(E6,KARY!$B$1:$C$62016,2,FALSE)),0,(VLOOKUP(E6,KARY!$B$1:$C$62016,2,FALSE))) -> 0 | F8: =IF(ISERROR(VLOOKUP(F6,KARY!$B$1:$C$62016,2,FALSE)),0,(VLOOKUP(F6,KARY!$B$1:$C$62016,2,FALSE))) -> 0 | G8: =IF(ISERROR(VLOOKUP(G6,KARY!$B$1:$C$62016,2,FALSE)),0,(VLOOKUP(G6,KARY!$B$1:$C$62016,2,FALSE))) -> 0 | H8: =IF(ISERROR(VLOOKUP(H6,KARY!$B$1:$C$62016,2,FALSE)),0,(VLOOKUP(H6,KARY!$B$1:$C$62016,2,FALSE))) -> 0 | I8: =IF(ISERROR(VLOOKUP(I6,KARY!$B$1:$C$62016,2,FALSE)),0,(VLOOKUP(I6,KARY!$B$1:$C$62016,2,FALSE))) -> 0 | J8: =IF(ISERROR(VLOOKUP(J6,KARY!$B$1:$C$62016,2,FALSE)),0,(VLOOKUP(J6,KARY!$B$1:$C$62016,2,FALSE))) -> 0 | ... V8: =IF(ISERROR(VLOOKUP(V6,KARY!$B$1:$C$62016,2,FALSE)),0,(VLOOKUP(V6,KARY!$B$1:$C$62016,2,FALSE))) -> 0
B10: =ANALISA!C8 -> 46266 | C10: =SUMIFS(statement!$J:$J,statement!$K:$K,ANALISA!$AA8, statement!$A:$A,C$6) -> 0 | D10: =SUMIFS(statement!$J:$J,statement!$K:$K,ANALISA!$AA8, statement!$A:$A,D$6) -> 0 | E10: =SUMIFS(statement!$J:$J,statement!$K:$K,ANALISA!$AA8, statement!$A:$A,E$6) -> 0 | F10: =SUMIFS(statement!$J:$J,statement!$K:$K,ANALISA!$AA8, statement!$A:$A,F$6) -> 0 | G10: =SUMIFS(statement!$J:$J,statement!$K:$K,ANALISA!$AA8, statement!$A:$A,G$6) -> 0 | H10: =SUMIFS(statement!$J:$J,statement!$K:$K,ANALISA!$AA8, statement!$A:$A,H$6) -> 0 | I10: =SUMIFS(statement!$J:$J,statement!$K:$K,ANALISA!$AA8, statement!$A:$A,I$6) -> 0 | J10: =SUMIFS(statement!$J:$J,statement!$K:$K,ANALISA!$AA8, statement!$A:$A,J$6) -> 0 | ... AI10: =SUMIFS(statement!$J:$J,statement!$K:$K,ANALISA!$AA8, statement!$A:$A,AI$6) -> 0 | AJ10: =ANALISA!AB8 -> 0 | AK10: =SUM(C10:AI10) -> 0 | AL10: =IF(SUMIF(statement!$K:$K,ANALISA!AA8,statement!$J:$J)=AK10,"MATCH","UNMATCH") -> MATCH | AM10: =AK10-ANALISA!R8 -> 0
B11: =ANALISA!C9 -> 46267 | C11: =SUMIFS(statement!$J:$J,statement!$K:$K,ANALISA!$AA9, statement!$A:$A,C$6) -> 0 | D11: =SUMIFS(statement!$J:$J,statement!$K:$K,ANALISA!$AA9, statement!$A:$A,D$6) -> 0 | E11: =SUMIFS(statement!$J:$J,statement!$K:$K,ANALISA!$AA9, statement!$A:$A,E$6) -> 0 | F11: =SUMIFS(statement!$J:$J,statement!$K:$K,ANALISA!$AA9, statement!$A:$A,F$6) -> 0 | G11: =SUMIFS(statement!$J:$J,statement!$K:$K,ANALISA!$AA9, statement!$A:$A,G$6) -> 0 | H11: =SUMIFS(statement!$J:$J,statement!$K:$K,ANALISA!$AA9, statement!$A:$A,H$6) -> 0 | I11: =SUMIFS(statement!$J:$J,statement!$K:$K,ANALISA!$AA9, statement!$A:$A,I$6) -> 0 | J11: =SUMIFS(statement!$J:$J,statement!$K:$K,ANALISA!$AA9, statement!$A:$A,J$6) -> 0 | ... AI11: =SUMIFS(statement!$J:$J,statement!$K:$K,ANALISA!$AA9, statement!$A:$A,AI$6) -> 0 | AJ11: =ANALISA!AB9 -> 0 | AK11: =SUM(C11:AI11) -> 0 | AL11: =IF(SUMIF(statement!$K:$K,ANALISA!AA9,statement!$J:$J)=AK11,"MATCH","UNMATCH") -> MATCH | AM11: =AK11-ANALISA!R9 -> 0
B12: =ANALISA!C10 -> 46268 | C12: =SUMIFS(statement!$J:$J,statement!$K:$K,ANALISA!$AA10, statement!$A:$A,C$6) -> 0 | D12: =SUMIFS(statement!$J:$J,statement!$K:$K,ANALISA!$AA10, statement!$A:$A,D$6) -> 0 | E12: =SUMIFS(statement!$J:$J,statement!$K:$K,ANALISA!$AA10, statement!$A:$A,E$6) -> 0 | F12: =SUMIFS(statement!$J:$J,statement!$K:$K,ANALISA!$AA10, statement!$A:$A,F$6) -> 0 | G12: =SUMIFS(statement!$J:$J,statement!$K:$K,ANALISA!$AA10, statement!$A:$A,G$6) -> 0 | H12: =SUMIFS(statement!$J:$J,statement!$K:$K,ANALISA!$AA10, statement!$A:$A,H$6) -> 0 | I12: =SUMIFS(statement!$J:$J,statement!$K:$K,ANALISA!$AA10, statement!$A:$A,I$6) -> 0 | J12: =SUMIFS(statement!$J:$J,statement!$K:$K,ANALISA!$AA10, statement!$A:$A,J$6) -> 0 | ... AI12: =SUMIFS(statement!$J:$J,statement!$K:$K,ANALISA!$AA10, statement!$A:$A,AI$6) -> 0 | AJ12: =ANALISA!AB10 -> 0 | AK12: =SUM(C12:AI12) -> 0 | AL12: =IF(SUMIF(statement!$K:$K,ANALISA!AA10,statement!$J:$J)=AK12,"MATCH","UNMATCH") -> MATCH | AM12: =AK12-ANALISA!R10 -> 0
B13: =ANALISA!C11 -> 46269 | C13: =SUMIFS(statement!$J:$J,statement!$K:$K,ANALISA!$AA11, statement!$A:$A,C$6) -> 0 | D13: =SUMIFS(statement!$J:$J,statement!$K:$K,ANALISA!$AA11, statement!$A:$A,D$6) -> 0 | E13: =SUMIFS(statement!$J:$J,statement!$K:$K,ANALISA!$AA11, statement!$A:$A,E$6) -> 0 | F13: =SUMIFS(statement!$J:$J,statement!$K:$K,ANALISA!$AA11, statement!$A:$A,F$6) -> 0 | G13: =SUMIFS(statement!$J:$J,statement!$K:$K,ANALISA!$AA11, statement!$A:$A,G$6) -> 0 | H13: =SUMIFS(statement!$J:$J,statement!$K:$K,ANALISA!$AA11, statement!$A:$A,H$6) -> 0 | I13: =SUMIFS(statement!$J:$J,statement!$K:$K,ANALISA!$AA11, statement!$A:$A,I$6) -> 0 | J13: =SUMIFS(statement!$J:$J,statement!$K:$K,ANALISA!$AA11, statement!$A:$A,J$6) -> 0 | ... AI13: =SUMIFS(statement!$J:$J,statement!$K:$K,ANALISA!$AA11, statement!$A:$A,AI$6) -> 0 | AJ13: =ANALISA!AB11 -> 0 | AK13: =SUM(C13:AI13) -> 0 | AL13: =IF(SUMIF(statement!$K:$K,ANALISA!AA11,statement!$J:$J)=AK13,"MATCH","UNMATCH") -> MATCH | AM13: =AK13-ANALISA!R11 -> 0
B14: =ANALISA!C12 -> 46270 | C14: =SUMIFS(statement!$J:$J,statement!$K:$K,ANALISA!$AA12, statement!$A:$A,C$6) -> 0 | D14: =SUMIFS(statement!$J:$J,statement!$K:$K,ANALISA!$AA12, statement!$A:$A,D$6) -> 0 | E14: =SUMIFS(statement!$J:$J,statement!$K:$K,ANALISA!$AA12, statement!$A:$A,E$6) -> 0 | F14: =SUMIFS(statement!$J:$J,statement!$K:$K,ANALISA!$AA12, statement!$A:$A,F$6) -> 0 | G14: =SUMIFS(statement!$J:$J,statement!$K:$K,ANALISA!$AA12, statement!$A:$A,G$6) -> 0 | H14: =SUMIFS(statement!$J:$J,statement!$K:$K,ANALISA!$AA12, statement!$A:$A,H$6) -> 0 | I14: =SUMIFS(statement!$J:$J,statement!$K:$K,ANALISA!$AA12, statement!$A:$A,I$6) -> 0 | J14: =SUMIFS(statement!$J:$J,statement!$K:$K,ANALISA!$AA12, statement!$A:$A,J$6) -> 0 | ... AI14: =SUMIFS(statement!$J:$J,statement!$K:$K,ANALISA!$AA12, statement!$A:$A,AI$6) -> 0 | AJ14: =ANALISA!AB12 -> 0 | AK14: =SUM(C14:AI14) -> 0 | AL14: =IF(SUMIF(statement!$K:$K,ANALISA!AA12,statement!$J:$J)=AK14,"MATCH","UNMATCH") -> MATCH | AM14: =AK14-ANALISA!R12 -> 0
B15: =ANALISA!C13 -> 46271 | C15: =SUMIFS(statement!$J:$J,statement!$K:$K,ANALISA!$AA13, statement!$A:$A,C$6) -> 0 | D15: =SUMIFS(statement!$J:$J,statement!$K:$K,ANALISA!$AA13, statement!$A:$A,D$6) -> 0 | E15: =SUMIFS(statement!$J:$J,statement!$K:$K,ANALISA!$AA13, statement!$A:$A,E$6) -> 0 | F15: =SUMIFS(statement!$J:$J,statement!$K:$K,ANALISA!$AA13, statement!$A:$A,F$6) -> 0 | G15: =SUMIFS(statement!$J:$J,statement!$K:$K,ANALISA!$AA13, statement!$A:$A,G$6) -> 0 | H15: =SUMIFS(statement!$J:$J,statement!$K:$K,ANALISA!$AA13, statement!$A:$A,H$6) -> 0 | I15: =SUMIFS(statement!$J:$J,statement!$K:$K,ANALISA!$AA13, statement!$A:$A,I$6) -> 0 | J15: =SUMIFS(statement!$J:$J,statement!$K:$K,ANALISA!$AA13, statement!$A:$A,J$6) -> 0 | ... AI15: =SUMIFS(statement!$J:$J,statement!$K:$K,ANALISA!$AA13, statement!$A:$A,AI$6) -> 0 | AJ15: =ANALISA!AB13 -> 0 | AK15: =SUM(C15:AI15) -> 0 | AL15: =IF(SUMIF(statement!$K:$K,ANALISA!AA13,statement!$J:$J)=AK15,"MATCH","UNMATCH") -> MATCH | AM15: =AK15-ANALISA!R13 -> 0
B16: =ANALISA!C14 -> 46272 | C16: =SUMIFS(statement!$J:$J,statement!$K:$K,ANALISA!$AA14, statement!$A:$A,C$6) -> 0 | D16: =SUMIFS(statement!$J:$J,statement!$K:$K,ANALISA!$AA14, statement!$A:$A,D$6) -> 0 | E16: =SUMIFS(statement!$J:$J,statement!$K:$K,ANALISA!$AA14, statement!$A:$A,E$6) -> 0 | F16: =SUMIFS(statement!$J:$J,statement!$K:$K,ANALISA!$AA14, statement!$A:$A,F$6) -> 0 | G16: =SUMIFS(statement!$J:$J,statement!$K:$K,ANALISA!$AA14, statement!$A:$A,G$6) -> 0 | H16: =SUMIFS(statement!$J:$J,statement!$K:$K,ANALISA!$AA14, statement!$A:$A,H$6) -> 0 | I16: =SUMIFS(statement!$J:$J,statement!$K:$K,ANALISA!$AA14, statement!$A:$A,I$6) -> 0 | J16: =SUMIFS(statement!$J:$J,statement!$K:$K,ANALISA!$AA14, statement!$A:$A,J$6) -> 0 | ... AI16: =SUMIFS(statement!$J:$J,statement!$K:$K,ANALISA!$AA14, statement!$A:$A,AI$6) -> 0 | AJ16: =ANALISA!AB14 -> 0 | AK16: =SUM(C16:AI16) -> 0 | AL16: =IF(SUMIF(statement!$K:$K,ANALISA!AA14,statement!$J:$J)=AK16,"MATCH","UNMATCH") -> MATCH | AM16: =AK16-ANALISA!R14 -> 0
B17: =ANALISA!C15 -> 46273 | C17: =SUMIFS(statement!$J:$J,statement!$K:$K,ANALISA!$AA15, statement!$A:$A,C$6) -> 0 | D17: =SUMIFS(statement!$J:$J,statement!$K:$K,ANALISA!$AA15, statement!$A:$A,D$6) -> 0 | E17: =SUMIFS(statement!$J:$J,statement!$K:$K,ANALISA!$AA15, statement!$A:$A,E$6) -> 0 | F17: =SUMIFS(statement!$J:$J,statement!$K:$K,ANALISA!$AA15, statement!$A:$A,F$6) -> 0 | G17: =SUMIFS(statement!$J:$J,statement!$K:$K,ANALISA!$AA15, statement!$A:$A,G$6) -> 0 | H17: =SUMIFS(statement!$J:$J,statement!$K:$K,ANALISA!$AA15, statement!$A:$A,H$6) -> 0 | I17: =SUMIFS(statement!$J:$J,statement!$K:$K,ANALISA!$AA15, statement!$A:$A,I$6) -> 0 | J17: =SUMIFS(statement!$J:$J,statement!$K:$K,ANALISA!$AA15, statement!$A:$A,J$6) -> 0 | ... AI17: =SUMIFS(statement!$J:$J,statement!$K:$K,ANALISA!$AA15, statement!$A:$A,AI$6) -> 0 | AJ17: =ANALISA!AB15 -> 0 | AK17: =SUM(C17:AI17) -> 0 | AL17: =IF(SUMIF(statement!$K:$K,ANALISA!AA15,statement!$J:$J)=AK17,"MATCH","UNMATCH") -> MATCH | AM17: =AK17-ANALISA!R15 -> 0
B18: =ANALISA!C16 -> 46274 | C18: =SUMIFS(statement!$J:$J,statement!$K:$K,ANALISA!$AA16, statement!$A:$A,C$6) -> 0 | D18: =SUMIFS(statement!$J:$J,statement!$K:$K,ANALISA!$AA16, statement!$A:$A,D$6) -> 0 | E18: =SUMIFS(statement!$J:$J,statement!$K:$K,ANALISA!$AA16, statement!$A:$A,E$6) -> 0 | F18: =SUMIFS(statement!$J:$J,statement!$K:$K,ANALISA!$AA16, statement!$A:$A,F$6) -> 0 | G18: =SUMIFS(statement!$J:$J,statement!$K:$K,ANALISA!$AA16, statement!$A:$A,G$6) -> 0 | H18: =SUMIFS(statement!$J:$J,statement!$K:$K,ANALISA!$AA16, statement!$A:$A,H$6) -> 0 | I18: =SUMIFS(statement!$J:$J,statement!$K:$K,ANALISA!$AA16, statement!$A:$A,I$6) -> 0 | J18: =SUMIFS(statement!$J:$J,statement!$K:$K,ANALISA!$AA16, statement!$A:$A,J$6) -> 0 | ... AI18: =SUMIFS(statement!$J:$J,statement!$K:$K,ANALISA!$AA16, statement!$A:$A,AI$6) -> 0 | AJ18: =ANALISA!AB16 -> 0 | AK18: =SUM(C18:AI18) -> 0 | AL18: =IF(SUMIF(statement!$K:$K,ANALISA!AA16,statement!$J:$J)=AK18,"MATCH","UNMATCH") -> MATCH | AM18: =AK18-ANALISA!R16 -> 0
B19: =ANALISA!C17 -> 46275 | C19: =SUMIFS(statement!$J:$J,statement!$K:$K,ANALISA!$AA17, statement!$A:$A,C$6) -> 0 | D19: =SUMIFS(statement!$J:$J,statement!$K:$K,ANALISA!$AA17, statement!$A:$A,D$6) -> 0 | E19: =SUMIFS(statement!$J:$J,statement!$K:$K,ANALISA!$AA17, statement!$A:$A,E$6) -> 0 | F19: =SUMIFS(statement!$J:$J,statement!$K:$K,ANALISA!$AA17, statement!$A:$A,F$6) -> 0 | G19: =SUMIFS(statement!$J:$J,statement!$K:$K,ANALISA!$AA17, statement!$A:$A,G$6) -> 0 | H19: =SUMIFS(statement!$J:$J,statement!$K:$K,ANALISA!$AA17, statement!$A:$A,H$6) -> 0 | I19: =SUMIFS(statement!$J:$J,statement!$K:$K,ANALISA!$AA17, statement!$A:$A,I$6) -> 0 | J19: =SUMIFS(statement!$J:$J,statement!$K:$K,ANALISA!$AA17, statement!$A:$A,J$6) -> 0 | ... AI19: =SUMIFS(statement!$J:$J,statement!$K:$K,ANALISA!$AA17, statement!$A:$A,AI$6) -> 0 | AJ19: =ANALISA!AB17 -> 0 | AK19: =SUM(C19:AI19) -> 0 | AL19: =IF(SUMIF(statement!$K:$K,ANALISA!AA17,statement!$J:$J)=AK19,"MATCH","UNMATCH") -> MATCH | AM19: =AK19-ANALISA!R17 -> 0
B20: =ANALISA!C18 -> 46276 | C20: =SUMIFS(statement!$J:$J,statement!$K:$K,ANALISA!$AA18, statement!$A:$A,C$6) -> 0 | D20: =SUMIFS(statement!$J:$J,statement!$K:$K,ANALISA!$AA18, statement!$A:$A,D$6) -> 0 | E20: =SUMIFS(statement!$J:$J,statement!$K:$K,ANALISA!$AA18, statement!$A:$A,E$6) -> 0 | F20: =SUMIFS(statement!$J:$J,statement!$K:$K,ANALISA!$AA18, statement!$A:$A,F$6) -> 0 | G20: =SUMIFS(statement!$J:$J,statement!$K:$K,ANALISA!$AA18, statement!$A:$A,G$6) -> 0 | H20: =SUMIFS(statement!$J:$J,statement!$K:$K,ANALISA!$AA18, statement!$A:$A,H$6) -> 0 | I20: =SUMIFS(statement!$J:$J,statement!$K:$K,ANALISA!$AA18, statement!$A:$A,I$6) -> 0 | J20: =SUMIFS(statement!$J:$J,statement!$K:$K,ANALISA!$AA18, statement!$A:$A,J$6) -> 0 | ... AI20: =SUMIFS(statement!$J:$J,statement!$K:$K,ANALISA!$AA18, statement!$A:$A,AI$6) -> 0 | AJ20: =ANALISA!AB18 -> 0 | AK20: =SUM(C20:AI20) -> 0 | AL20: =IF(SUMIF(statement!$K:$K,ANALISA!AA18,statement!$J:$J)=AK20,"MATCH","UNMATCH") -> MATCH | AM20: =AK20-ANALISA!R18 -> 0
B21: =ANALISA!C19 -> 46277 | C21: =SUMIFS(statement!$J:$J,statement!$K:$K,ANALISA!$AA19, statement!$A:$A,C$6) -> 0 | D21: =SUMIFS(statement!$J:$J,statement!$K:$K,ANALISA!$AA19, statement!$A:$A,D$6) -> 0 | E21: =SUMIFS(statement!$J:$J,statement!$K:$K,ANALISA!$AA19, statement!$A:$A,E$6) -> 0 | F21: =SUMIFS(statement!$J:$J,statement!$K:$K,ANALISA!$AA19, statement!$A:$A,F$6) -> 0 | G21: =SUMIFS(statement!$J:$J,statement!$K:$K,ANALISA!$AA19, statement!$A:$A,G$6) -> 0 | H21: =SUMIFS(statement!$J:$J,statement!$K:$K,ANALISA!$AA19, statement!$A:$A,H$6) -> 0 | I21: =SUMIFS(statement!$J:$J,statement!$K:$K,ANALISA!$AA19, statement!$A:$A,I$6) -> 0 | J21: =SUMIFS(statement!$J:$J,statement!$K:$K,ANALISA!$AA19, statement!$A:$A,J$6) -> 0 | ... AI21: =SUMIFS(statement!$J:$J,statement!$K:$K,ANALISA!$AA19, statement!$A:$A,AI$6) -> 0 | AJ21: =ANALISA!AB19 -> 0 | AK21: =SUM(C21:AI21) -> 0 | AL21: =IF(SUMIF(statement!$K:$K,ANALISA!AA19,statement!$J:$J)=AK21,"MATCH","UNMATCH") -> MATCH | AM21: =AK21-ANALISA!R19 -> 0
... B40: =ANALISA!C38 -> 46296 | C40: =SUMIFS(statement!$J:$J,statement!$K:$K,ANALISA!$AA38, statement!$A:$A,C$6) -> 0 | D40: =SUMIFS(statement!$J:$J,statement!$K:$K,ANALISA!$AA38, statement!$A:$A,D$6) -> 0 | E40: =SUMIFS(statement!$J:$J,statement!$K:$K,ANALISA!$AA38, statement!$A:$A,E$6) -> 0 | F40: =SUMIFS(statement!$J:$J,statement!$K:$K,ANALISA!$AA38, statement!$A:$A,F$6) -> 0 | G40: =SUMIFS(statement!$J:$J,statement!$K:$K,ANALISA!$AA38, statement!$A:$A,G$6) -> 0 | H40: =SUMIFS(statement!$J:$J,statement!$K:$K,ANALISA!$AA38, statement!$A:$A,H$6) -> 0 | I40: =SUMIFS(statement!$J:$J,statement!$K:$K,ANALISA!$AA38, statement!$A:$A,I$6) -> 0 | J40: =SUMIFS(statement!$J:$J,statement!$K:$K,ANALISA!$AA38, statement!$A:$A,J$6) -> 0 | ... AI40: =SUMIFS(statement!$J:$J,statement!$K:$K,ANALISA!$AA38, statement!$A:$A,AI$6) -> 0 | AJ40: =ANALISA!AB38 -> 0 | AK40: =SUM(C40:AI40) -> 0 | AL40: =IF(SUMIF(statement!$K:$K,ANALISA!AA38,statement!$J:$J)=AK40,"MATCH","UNMATCH") -> MATCH | AM40: =AK40-ANALISA!R38 -> 0
B42: TOTAL SHORTAGE | C42: =SUM(C9:C41) -> 0 | D42: =SUM(D9:D41) -> 0 | E42: =SUM(E9:E41) -> 0 | F42: =SUM(F9:F41) -> 0 | G42: =SUM(G9:G41) -> 0 | H42: =SUM(H9:H41) -> 0 | I42: =SUM(I9:I41) -> 0 | J42: =SUM(J9:J41) -> 0 | ... AI42: =SUM(AI9:AI41) -> 0
B43: TOTAL MINUS | C43: =SUMIF(C10:C40,"<0") -> 0 | D43: =SUMIF(D10:D40,"<0") -> 0 | E43: =SUMIF(E10:E40,"<0") -> 0 | F43: =SUMIF(F10:F40,"<0") -> 0 | G43: =SUMIF(G10:G40,"<0") -> 0 | H43: =SUMIF(H10:H40,"<0") -> 0 | I43: =SUMIF(I10:I40,"<0") -> 0 | J43: =SUMIF(J10:J40,"<0") -> 0 | ... AI43: =SUMIF(AI10:AI40,"<0") -> 0 | AL43: =SUM(C43:AI43) -> 0

Sheet RK

Sheet BDEPO

Sheet statement

Sheet KARY
B1: NIK | C1: NAMA
B2: 88170 | C2: ILHAM TAUFIK HIDAYAT
B3: 101422 | C3: FAJAR YUDHI PRASETYO
B4: 1917 | C4: VISSIA AGNES TRI REJEKI
B5: 3122 | C5: YULFINA
B6: 3303 | C6: BUDI SANTOSO
B7: 5216 | C7: ARIF HARTONO
B8: 10696 | C8: N YETI NURBAETI
B9: 31522 | C9: SAFIRA ELYAFEI
B10: 33577 | C10: AULIA NANDA RATIH FADILLAH
B11: 53726 | C11: MARIA JEANETE JAWA
B12: 82071 | C12: AKHMAD SULTAN MASHURIDHO
B13: 90471 | C13: MUHAMMAD FIKRY KURNIAWAN
... B3579: 71483 | C3579: YACOBUS PRIYO UTOMO
